with_utils/__init__.py
with_utils/iter.py
with_utils-0.2.1.dist-info/WHEEL
with_utils-0.2.1.dist-info/METADATA
with_utils-0.2.1.dist-info/RECORD
