Metadata-Version: 2.1
Name: with-utils
Version: 0.2.1
Summary: WITH utils
Home-page: https://github.com/WithIO/with-utils
License: WTFPL
Author: Rémy Sanchez
Author-email: remy.sanchez@with-madrid.com
Requires-Python: >=3.6,<4.0
Classifier: License :: Other/Proprietary License
Classifier: Programming Language :: Python :: 3
Classifier: Programming Language :: Python :: 3.6
Classifier: Programming Language :: Python :: 3.7
Classifier: Programming Language :: Python :: 3.8
Project-URL: Repository, https://github.com/WithIO/with-utils
